chatgpt_command_line/__init__.py
chatgpt_command_line/main.py
chatgpt_command_line/markdown.py
chatgpt_command_line/model.py
chatgpt_command_line/view.py
chatgpt_command_line-0.1.5.dist-info/METADATA
chatgpt_command_line-0.1.5.dist-info/WHEEL
chatgpt_command_line-0.1.5.dist-info/entry_points.txt
chatgpt_command_line-0.1.5.dist-info/RECORD
