Metadata-Version: 2.1
Name: chatgpt-command-line
Version: 0.1.5
Summary: 
Author: obahamonde
Author-email: oscarmartinbahamondemunoz@gmail.com
Requires-Python: >=3.10,<3.13
Classifier: Programming Language :: Python :: 3
Classifier: Programming Language :: Python :: 3.10
Classifier: Programming Language :: Python :: 3.11
Requires-Dist: click (>=8.1.7,<9.0.0)
Requires-Dist: flask (>=3.0.0,<4.0.0)
Requires-Dist: linkify (>=1.4,<2.0)
Requires-Dist: numpy (>=1.26.1,<2.0.0)
Requires-Dist: openai (>=0.28.1,<0.29.0)
Requires-Dist: pydantic (==1.10.12)
Requires-Dist: rich (>=13.6.0,<14.0.0)
Requires-Dist: tenacity (>=8.2.3,<9.0.0)
Requires-Dist: tiktoken (>=0.5.1,<0.6.0)
